{
    "open": false,
    "type": "folder",
    "name": "Desktop",
    "children": [
        {
            "name": "test1",
            "open": false,
            "type": "folder",
            "position": 0
        },
        {
            "name": "test2",
            "open": false,
            "type": "folder",
            "position": 1
        },
        {
            "name": "test3",
            "open": false,
            "type": "folder",
            "position": 9
        },
        {
            "name": "test6",
            "open": false,
            "type": "folder",
            "position": 8
        }
    ]
}